Metadata-Version: 1.1
Name: grokproject
Version: 2.12
Summary: Script that creates a Grok project directory, installs Grok, the Grok Toolkit and the Zope Toolkit and sets up a complete skeleton for a new Grok web application.
Home-page: http://grok.zope.org
Author: Grok Team
Author-email: grok-dev@zope.org
License: ZPL
Download-URL: https://pypi.python.org/pypi/grokproject
Platform: UNKNOWN
